{"data_mtime": 1589304291, "dep_lines": [2, 4, 5, 6, 7, 9, 1, 1, 1, 1, 1, 1], "dep_prios": [5, 10, 10, 10, 10, 5, 5, 30, 30, 10, 20, 20], "dependencies": ["depth_generation", "argparse", "shutil", "os", "time", "replace_poses", "builtins", "abc", "typing"], "hash": "58a5f6cc73ded79e3ad2219930fd07b5045766c241b29603360b14efadd4df6d", "id": "pipe_joint", "ignore_all": false, "interface_hash": "92264c4338925b3a6f81cd78d61863dcb72eaa46f5653ca54a09677bbb3bc706", "mtime": 1589304572, "options": {"allow_redefinition": false, "allow_untyped_globals": false, "always_false": [], "always_true": [], "bazel": false, "check_untyped_defs": false, "disallow_any_decorated": false, "disallow_any_explicit": false, "disallow_any_expr": false, "disallow_any_generics": false, "disallow_any_unimported": false, "disallow_incomplete_defs": false, "disallow_subclassing_any": false, "disallow_untyped_calls": false, "disallow_untyped_decorators": false, "disallow_untyped_defs": false, "follow_imports": "silent", "follow_imports_for_stubs": false, "ignore_errors": false, "ignore_missing_imports": true, "implicit_reexport": true, "local_partial_types": false, "mypyc": false, "no_implicit_optional": false, "platform": "linux", "plugins": [], "show_none_errors": true, "strict_equality": false, "strict_optional": true, "strict_optional_whitelist": null, "warn_no_return": true, "warn_return_any": false, "warn_unreachable": false, "warn_unused_ignores": false}, "path": "/home/kudo/devs/pytorch-dense-correspondence/scripts/pipe_joint.py", "plugin_data": null, "size": 5959, "suppressed": ["dense_correspondence_manipulation.utils.utils", "dense_correspondence_manipulation", "dense_correspondence_manipulation.utils"], "version_id": "0.770"}